.coveragerc
.gitlab-ci.yml
AUTHORS
ChangeLog
Makefile
README.md
requirements-doc.txt
requirements.txt
setup.cfg
setup.py
tox.ini
doc/index.md
doc/mkdocs.yml
doc/mkdocs_.yml
doc/rxdata/index.md
doc/rxdata/typeguard.md
doc/script/toc/markdown.py
doc/script/toc/mkdocs.py
rx_dataclasses.egg-info/PKG-INFO
rx_dataclasses.egg-info/SOURCES.txt
rx_dataclasses.egg-info/dependency_links.txt
rx_dataclasses.egg-info/not-zip-safe
rx_dataclasses.egg-info/pbr.json
rx_dataclasses.egg-info/requires.txt
rx_dataclasses.egg-info/top_level.txt
rxdata/__init__.py
rxdata/attribute.py
rxdata/operators.py
tests/features/compatibility.rxdata.dataclass.feature
tests/features/evolution.dataclass.feature
tests/features/observation.dataclass.feature
tests/features/sample/class/evolution.py
tests/features/sample/class/observation.py
tests/features/sample/class/transparency.py
tests/features/steps/unitteststeps.py
tests/features/unit/conftest.py
tests/features/unit/pytest.ini
tests/features/unit/test_rxdata_evolution.py
tests/features/unit/test_rxdata_observation.py
tests/features/unit/test_rxdata_transparency.py