Metadata-Version: 2.1
Name: rx-dataclasses
Version: 0.0.4
Summary: dataclasses with verifiers/converters
Home-page: UNKNOWN
Author: Denis Mishchishin
Author-email: dennz78@gmail.com
License: MIT
Project-URL: Home, https://gitlab.com/denz1/rxdata
Project-URL: Documentation, https://rxdata.gitlab.io
Platform: UNKNOWN
Classifier: Development Status :: 3 - Alpha
Classifier: Environment :: Console
Classifier: License :: OSI Approved :: MIT License
Classifier: Intended Audience :: Developers
Classifier: Intended Audience :: Information Technology
Classifier: Natural Language :: English
Classifier: Operating System :: POSIX :: Linux
Classifier: Programming Language :: Python :: 3
Classifier: Programming Language :: Python :: 3.6
Classifier: Programming Language :: Python :: 3.7
Classifier: Topic :: Utilities
